speks/__init__.py
speks/_version.py
speks/gender_lex.py
speks/gender_predictor.py
speks/tokenization.py
speks-0.0.1.dist-info/METADATA
speks-0.0.1.dist-info/RECORD
speks-0.0.1.dist-info/WHEEL
speks-0.0.1.dist-info/top_level.txt
tests/__init__.py
tests/test_prediction.py
tests/test_tokenization.py
