Metadata-Version: 2.1
Name: speks
Version: 0.0.1
Summary: Text-based gender prediction for Twitter.
Home-page: https://github.com/shaypal5/speks
Author: Shay Palachy
Author-email: shay.palachy@gmail.com
License: MPL2.0
Platform: UNKNOWN
Classifier: Development Status :: 4 - Beta
Classifier: License :: OSI Approved :: MIT License
Classifier: Programming Language :: Python
Classifier: Programming Language :: Python :: 3.4
Classifier: Programming Language :: Python :: 3.5
Classifier: Programming Language :: Python :: 3.6
Classifier: Topic :: Software Development :: Libraries
Classifier: Topic :: Software Development :: Libraries :: Python Modules
Classifier: Intended Audience :: Developers
Requires-Python: >=3.4
Provides-Extra: test
Provides-Extra: test
Requires-Dist: pytest; extra == 'test'
Requires-Dist: coverage; extra == 'test'
Requires-Dist: pytest-cov; extra == 'test'
Requires-Dist: collective.checkdocs; extra == 'test'
Requires-Dist: pygments; extra == 'test'
